[
  {
    "rowNum": 1,
    "type": "회의비",
    "purpose": "회의비",
    "amount": 2000000,
    "vendor": "강남한우정육식당",
    "status": "확인",
    "issues": [
      "내부결재문서 미첨부",
      "참석인원수 확인 필요 (OCR 인원 미파악)",
      "외부참석자(과제 미참여인력) 확인 필요"
    ],
    "ok": [
      "회의록 ✓",
      "영수증/카드전표 ✓"
    ]
  },
  {
    "rowNum": 2,
    "type": "임차",
    "purpose": "11/29 세브란스병원 중환자의학 심포지엄 부스비",
    "amount": 1000000,
    "vendor": "연세대학교 의료원",
    "status": "확인",
    "issues": [
      "계약서 미첨부",
      "검수조서 미첨부",
      "견적서 0개 (2개 이상 권장)"
    ],
    "ok": []
  },
  {
    "rowNum": 3,
    "type": "임차",
    "purpose": "11/6~8 대한외과학회 외_물품임대비",
    "amount": 1250000,
    "vendor": "주식회사 시나포유",
    "status": "확인",
    "issues": [
      "계약서 미첨부",
      "검수조서 미첨부",
      "★ 범용성 장비(노트북/PC) 대여 → 지침 별표2 3.4항 \"범용성 장비 구입 또는 대여\" 불인정"
    ],
    "ok": [
      "견적서 2개 ✓"
    ]
  },
  {
    "rowNum": 4,
    "type": "용역",
    "purpose": "11/6~8 대한외과학회 외_부스설치철거비",
    "amount": 3350000,
    "vendor": "주식회사 시나포유",
    "status": "확인",
    "issues": [
      "계약서 미첨부",
      "용역 결과보고서 미첨부",
      "세금계산서 미첨부"
    ],
    "ok": [
      "견적서 2개 ✓",
      "공급가액 3,350,000원 ≤ 2천만원 → 수의계약 적정 ✓"
    ]
  },
  {
    "rowNum": 5,
    "type": "임차",
    "purpose": "11/28-29 한국의료윤리학회 부스비",
    "amount": 3000000,
    "vendor": "한국의료윤리학회",
    "status": "확인",
    "issues": [
      "계약서 미첨부",
      "검수조서 미첨부",
      "견적서 0개 (2개 이상 권장)"
    ],
    "ok": []
  },
  {
    "rowNum": 6,
    "type": "자문료",
    "purpose": "자문수당_김예지",
    "amount": 3000000,
    "vendor": "김예지",
    "status": "확인",
    "issues": [
      "자문의견서 미첨부",
      "자문확인서 미첨부"
    ],
    "ok": [
      "외부전문가(김예지) ✓",
      "세전추정 3,102,378원 (자문시간 확인 필요)"
    ]
  },
  {
    "rowNum": 7,
    "type": "자문료",
    "purpose": "자문수당_고여경",
    "amount": 3000000,
    "vendor": "고여경",
    "status": "확인",
    "issues": [
      "자문의견서 미첨부",
      "자문확인서 미첨부"
    ],
    "ok": [
      "외부전문가(고여경) ✓",
      "세전추정 3,102,378원 (자문시간 확인 필요)"
    ]
  },
  {
    "rowNum": 8,
    "type": "인건비",
    "purpose": "참여연구원 12월 인건비",
    "amount": 6866666,
    "vendor": "주식회사 에이아이트릭스",
    "status": "적정",
    "issues": [],
    "ok": [
      "소득지급명세서 ✓",
      "근로계약서/참여율 → 별도 확인 필요"
    ]
  },
  {
    "rowNum": 9,
    "type": "임차",
    "purpose": "11/22 대한외상중환자외과학회 부스비",
    "amount": 3000000,
    "vendor": "대한외상중환자외과학회",
    "status": "확인",
    "issues": [
      "계약서 미첨부",
      "검수조서 미첨부",
      "견적서 0개 (2개 이상 권장)"
    ],
    "ok": []
  },
  {
    "rowNum": 10,
    "type": "임차",
    "purpose": "10/24~25 대한내과학회 외_물품임대비",
    "amount": 740000,
    "vendor": "주식회사 시나포유",
    "status": "확인",
    "issues": [
      "계약서 미첨부",
      "검수조서 미첨부"
    ],
    "ok": [
      "견적서 1개 (2천만원 이하 → 1인견적 가능)"
    ]
  },
  {
    "rowNum": 11,
    "type": "용역",
    "purpose": "10/24~25 대한내과학회 외_부스설치철거비",
    "amount": 1900000,
    "vendor": "주식회사 시나포유",
    "status": "확인",
    "issues": [
      "계약서 미첨부",
      "견적서 1개 (수의계약 시 2개 이상 필요)",
      "용역 결과보고서 미첨부",
      "세금계산서 미첨부"
    ],
    "ok": [
      "공급가액 1,900,000원 ≤ 2천만원 → 수의계약 적정 ✓"
    ]
  },
  {
    "rowNum": 12,
    "type": "임차",
    "purpose": "11/21 가톨릭대학교 성빈센트병원 제2회 스마트 의료 심포지엄_물품대여비",
    "amount": 500000,
    "vendor": "성빈센트병원",
    "status": "확인",
    "issues": [
      "계약서 미첨부",
      "검수조서 미첨부",
      "견적서 0개 (2개 이상 권장)",
      "★ 범용성 장비(노트북/PC) 대여 → 지침 별표2 3.4항 \"범용성 장비 구입 또는 대여\" 불인정"
    ],
    "ok": []
  },
  {
    "rowNum": 13,
    "type": "수수료",
    "purpose": "회계정산비",
    "amount": 723000,
    "vendor": "정동회계법인",
    "status": "적정",
    "issues": [],
    "ok": [
      "세금계산서/가상계좌 ✓",
      "수수료 → 일반수용비 적정"
    ]
  },
  {
    "rowNum": 14,
    "type": "사무용품",
    "purpose": "사무용품비 11월",
    "amount": 449550,
    "vendor": "알파주식회사",
    "status": "확인",
    "issues": [
      "세금계산서 미첨부",
      "★ 범용성 장비 구매 의심 → 지침 별표2 불인정 항목 확인"
    ],
    "ok": [
      "견적서 ✓",
      "거래명세서 ✓"
    ]
  },
  {
    "rowNum": 15,
    "type": "수수료",
    "purpose": "보고서인쇄비",
    "amount": 300000,
    "vendor": "（주）아임프린트",
    "status": "적정",
    "issues": [],
    "ok": [
      "수수료 → 일반수용비 적정"
    ]
  },
  {
    "rowNum": 16,
    "type": "기타",
    "purpose": "도서구입비",
    "amount": 382220,
    "vendor": "예스이십사 주식회사",
    "status": "확인",
    "issues": [
      "분류 불가 → 수동 확인 필요"
    ],
    "ok": []
  },
  {
    "rowNum": 17,
    "type": "임차",
    "purpose": "11/6-7 대한감염학회 부스비",
    "amount": 3000000,
    "vendor": "대한감염학회",
    "status": "확인",
    "issues": [
      "계약서 미첨부",
      "검수조서 미첨부",
      "견적서 0개 (2개 이상 권장)",
      "★ 범용성 장비(노트북/PC) 대여 → 지침 별표2 3.4항 \"범용성 장비 구입 또는 대여\" 불인정"
    ],
    "ok": []
  },
  {
    "rowNum": 18,
    "type": "임차",
    "purpose": "9/12 대한병원행정관리자협회 종합학술대회 물품대여비",
    "amount": 100000,
    "vendor": "주식회사 시나포유",
    "status": "확인",
    "issues": [
      "계약서 미첨부",
      "검수조서 미첨부",
      "견적서 0개 (2개 이상 권장)"
    ],
    "ok": []
  },
  {
    "rowNum": 19,
    "type": "임차",
    "purpose": "9/6 삼성서울병원 중환자의학연수강좌 물품대여비",
    "amount": 100000,
    "vendor": "주식회사 시나포유",
    "status": "확인",
    "issues": [
      "계약서 미첨부",
      "검수조서 미첨부",
      "견적서 0개 (2개 이상 권장)"
    ],
    "ok": []
  },
  {
    "rowNum": 20,
    "type": "수수료",
    "purpose": "전자수입인지",
    "amount": 70000,
    "vendor": "(사단법인) 금융결제원",
    "status": "적정",
    "issues": [],
    "ok": [
      "수수료 → 일반수용비 적정"
    ]
  },
  {
    "rowNum": 21,
    "type": "수수료",
    "purpose": "계약이행보증보험료",
    "amount": 20230,
    "vendor": "서울보증보험(주)서초지점",
    "status": "적정",
    "issues": [],
    "ok": [
      "수수료 → 일반수용비 적정"
    ]
  },
  {
    "rowNum": 22,
    "type": "사무용품",
    "purpose": "사무용품비_8~10월",
    "amount": 1515000,
    "vendor": "알파주식회사",
    "status": "확인",
    "issues": [
      "세금계산서 미첨부",
      "★ 범용성 장비 구매 의심 → 지침 별표2 불인정 항목 확인",
      "1,515,000원 → 50만원 초과, 자산취득 해당 여부 확인"
    ],
    "ok": [
      "견적서 ✓",
      "거래명세서 ✓"
    ]
  },
  {
    "rowNum": 23,
    "type": "인건비",
    "purpose": "참여연구원 11월 인건비",
    "amount": 6866667,
    "vendor": "주식회사 에이아이트릭스",
    "status": "적정",
    "issues": [],
    "ok": [
      "소득지급명세서 ✓",
      "근로계약서/참여율 → 별도 확인 필요"
    ]
  },
  {
    "rowNum": 24,
    "type": "인건비",
    "purpose": "참여연구원 10월 인건비",
    "amount": 6866667,
    "vendor": "주식회사 에이아이트릭스",
    "status": "적정",
    "issues": [],
    "ok": [
      "소득지급명세서 ✓",
      "근로계약서/참여율 → 별도 확인 필요"
    ]
  },
  {
    "rowNum": 25,
    "type": "임차",
    "purpose": "10/24-25 대한의료인공지능학회 부스비",
    "amount": 10000000,
    "vendor": "대한의료인공지능학회",
    "status": "확인",
    "issues": [
      "계약서 미첨부",
      "검수조서 미첨부",
      "견적서 0개 (2개 이상 권장)",
      "★ 범용성 장비(노트북/PC) 대여 → 지침 별표2 3.4항 \"범용성 장비 구입 또는 대여\" 불인정"
    ],
    "ok": []
  },
  {
    "rowNum": 26,
    "type": "임차",
    "purpose": "10/24-25 대한내과학회 부스비",
    "amount": 3000000,
    "vendor": "대한내과학회",
    "status": "확인",
    "issues": [
      "계약서 미첨부",
      "검수조서 미첨부",
      "견적서 0개 (2개 이상 권장)"
    ],
    "ok": []
  },
  {
    "rowNum": 27,
    "type": "임차",
    "purpose": "대한중환자의학회 호남지회 연수교육 물품대여비",
    "amount": 100000,
    "vendor": "주식회사 시나포유",
    "status": "확인",
    "issues": [
      "계약서 미첨부",
      "검수조서 미첨부",
      "견적서 0개 (2개 이상 권장)"
    ],
    "ok": []
  },
  {
    "rowNum": 28,
    "type": "용역",
    "purpose": "대한중환자의학회 호남지회 연수교육 부스설치/철거비",
    "amount": 900000,
    "vendor": "주식회사 시나포유",
    "status": "확인",
    "issues": [
      "계약서 미첨부",
      "견적서 0개 (수의계약 시 2개 이상 필요)",
      "용역 결과보고서 미첨부",
      "세금계산서 미첨부"
    ],
    "ok": [
      "공급가액 900,000원 ≤ 2천만원 → 수의계약 적정 ✓"
    ]
  },
  {
    "rowNum": 29,
    "type": "임차",
    "purpose": "9/12 대한병원행정관리자협회 종합학술대회 부스비",
    "amount": 3000000,
    "vendor": "사단법인 대한병원행정관리자협회",
    "status": "확인",
    "issues": [
      "계약서 미첨부",
      "검수조서 미첨부",
      "견적서 0개 (2개 이상 권장)",
      "★ 범용성 장비(노트북/PC) 대여 → 지침 별표2 3.4항 \"범용성 장비 구입 또는 대여\" 불인정"
    ],
    "ok": []
  },
  {
    "rowNum": 30,
    "type": "임차",
    "purpose": "9/6 대한중환자의학회 호남지회 연수강좌 부스비",
    "amount": 2000000,
    "vendor": "대한중환자의학회",
    "status": "확인",
    "issues": [
      "계약서 미첨부",
      "검수조서 미첨부",
      "견적서 0개 (2개 이상 권장)",
      "★ 범용성 장비(노트북/PC) 대여 → 지침 별표2 3.4항 \"범용성 장비 구입 또는 대여\" 불인정"
    ],
    "ok": []
  },
  {
    "rowNum": 31,
    "type": "임차",
    "purpose": "9/6 삼성서울병원 중환자의학연수강좌 부스비",
    "amount": 1000000,
    "vendor": "삼성서울병원",
    "status": "확인",
    "issues": [
      "계약서 미첨부",
      "검수조서 미첨부",
      "견적서 0개 (2개 이상 권장)"
    ],
    "ok": [
      "세금계산서 ✓"
    ]
  }
]